{"frames":{"01.png":{"frame":{"x":0,"y":0,"w":380,"h":380,"idx":0},"spriteSourceSize":{"x":0,"y":0},"sourceSize":{"w":380,"h":380}},"02.png":{"frame":{"x":0,"y":382,"w":380,"h":380,"idx":0},"spriteSourceSize":{"x":0,"y":0},"sourceSize":{"w":380,"h":380}},"03.png":{"frame":{"x":0,"y":764,"w":380,"h":380,"idx":0},"spriteSourceSize":{"x":0,"y":0},"sourceSize":{"w":380,"h":380}},"04.png":{"frame":{"x":0,"y":1146,"w":380,"h":380,"idx":0},"spriteSourceSize":{"x":0,"y":0},"sourceSize":{"w":380,"h":380}},"05.png":{"frame":{"x":382,"y":0,"w":380,"h":380,"idx":0},"spriteSourceSize":{"x":0,"y":0},"sourceSize":{"w":380,"h":380}},"06.png":{"frame":{"x":764,"y":0,"w":380,"h":380,"idx":0},"spriteSourceSize":{"x":0,"y":0},"sourceSize":{"w":380,"h":380}},"07.png":{"frame":{"x":1146,"y":0,"w":380,"h":380,"idx":0},"spriteSourceSize":{"x":0,"y":0},"sourceSize":{"w":380,"h":380}},"08.png":{"frame":{"x":382,"y":382,"w":380,"h":380,"idx":0},"spriteSourceSize":{"x":0,"y":0},"sourceSize":{"w":380,"h":380}},"09.png":{"frame":{"x":382,"y":764,"w":380,"h":380,"idx":0},"spriteSourceSize":{"x":0,"y":0},"sourceSize":{"w":380,"h":380}},"10.png":{"frame":{"x":382,"y":1146,"w":380,"h":380,"idx":0},"spriteSourceSize":{"x":0,"y":0},"sourceSize":{"w":380,"h":380}},"11.png":{"frame":{"x":764,"y":382,"w":380,"h":380,"idx":0},"spriteSourceSize":{"x":0,"y":0},"sourceSize":{"w":380,"h":380}},"12.png":{"frame":{"x":1146,"y":382,"w":380,"h":380,"idx":0},"spriteSourceSize":{"x":0,"y":0},"sourceSize":{"w":380,"h":380}},"13.png":{"frame":{"x":764,"y":764,"w":380,"h":380,"idx":0},"spriteSourceSize":{"x":0,"y":0},"sourceSize":{"w":380,"h":380}},"14.png":{"frame":{"x":764,"y":1146,"w":380,"h":380,"idx":0},"spriteSourceSize":{"x":0,"y":0},"sourceSize":{"w":380,"h":380}},"15.png":{"frame":{"x":1146,"y":764,"w":380,"h":380,"idx":0},"spriteSourceSize":{"x":0,"y":0},"sourceSize":{"w":380,"h":380}}},"meta":{"app":"http:\/\/www.layabox.com","version":"1.00","format":"json","scale":1,"image":"effect.png","prefix":"showhandRoom\/cardForm\/effect\/","md5":"bf8529bd79f6fefa60a27eaa785c38f5"}}
